CHANGES.rst
LICENSE.txt
README.rst
setup.cfg
setup.py
pyramid_pycallgraph/__init__.py
pyramid_pycallgraph.egg-info/PKG-INFO
pyramid_pycallgraph.egg-info/SOURCES.txt
pyramid_pycallgraph.egg-info/dependency_links.txt
pyramid_pycallgraph.egg-info/not-zip-safe
pyramid_pycallgraph.egg-info/requires.txt
pyramid_pycallgraph.egg-info/top_level.txt